async_graphql/__init__.py
async_graphql/client.py
async_graphql/errors.py
async_graphql-0.1.1.dist-info/METADATA
async_graphql-0.1.1.dist-info/WHEEL
async_graphql-0.1.1.dist-info/top_level.txt
async_graphql-0.1.1.dist-info/RECORD
