Metadata-Version: 2.1
Name: async-graphql
Version: 0.1.1
Summary: Async GraphQL client
Home-page: https://github.com/remorses/async-graphql
Author: Tommaso De Rossi
Author-email: beats.by.morse@gmail.com
License: MIT
Platform: UNKNOWN
Requires-Dist: six
Requires-Dist: asyncio
